Metadata-Version: 1.0
Name: pikaManagement
Version: 0.1.3
Summary: connect and consume with rabbitMq(pika)
Home-page: UNKNOWN
Author: zeinab
Author-email: zeinabzarei73@gmail.com
License: UNKNOWN
Platform: UNKNOWN
